{
    "meta":{
       "effective_params":{
          "data_set":"OANDA",
          "base_currencies":[
             "EUR"
          ],
          "quote_currencies":[
             "ADF",
             "ADP",
             "AED",
             "AFA",
             "AFN",
             "ALL",
             "AMD",
             "ANG",
             "AOA",
             "AON",
             "ARS",
             "ATS",
             "AUD",
             "AWG",
             "AZM",
             "AZN",
             "BAM",
             "BBD",
             "BDT",
             "BEF",
             "BGL",
             "BGN",
             "BHD",
             "BIF",
             "BMD",
             "BND",
             "BOB",
             "BRL",
             "BSD",
             "BTC",
             "BTN",
             "BWP",
             "BYN",
             "BYR",
             "BZD",
             "CAD",
             "CDF",
             "CFP",
             "CHF",
             "CLP",
             "CNH",
             "CNY",
             "COP",
             "CRC",
             "CSD",
             "CSK",
             "CUC",
             "CUP",
             "CVE",
             "CYP",
             "CZK",
             "DEM",
             "DJF",
             "DKK",
             "DOP",
             "DZD",
             "ECS",
             "EEK",
             "EGP",
             "ERN",
             "ESP",
             "ETB",
             "ETH",
             "FIM",
             "FJD",
             "FKP",
             "FRF",
             "GBP",
             "GEL",
             "GHC",
             "GHS",
             "GIP",
             "GMD",
             "GNF",
             "GRD",
             "GTQ",
             "GYD",
             "HKD",
             "HNL",
             "HRK",
             "HTG",
             "HUF",
             "IDR",
             "IEP",
             "ILS",
             "INR",
             "IQD",
             "IRR",
             "ISK",
             "ITL",
             "JMD",
             "JOD",
             "JPY",
             "KES",
             "KGS",
             "KHR",
             "KMF",
             "KPW",
             "KRW",
             "KWD",
             "KYD",
             "KZT",
             "LAK",
             "LBP",
             "LKR",
             "LRD",
             "LSL",
             "LTC",
             "LTL",
             "LUF",
             "LVL",
             "LYD",
             "MAD",
             "MDL",
             "MGA",
             "MGF",
             "MKD",
             "MMK",
             "MNT",
             "MOP",
             "MRO",
             "MRU",
             "MTL",
             "MUR",
             "MVR",
             "MWK",
             "MXN",
             "MXP",
             "MYR",
             "MZM",
             "MZN",
             "NAD",
             "NGN",
             "NIO",
             "NLG",
             "NOK",
             "NPR",
             "NZD",
             "OMR",
             "PAB",
             "PEN",
             "PGK",
             "PHP",
             "PKR",
             "PLN",
             "PLZ",
             "PTE",
             "PYG",
             "QAR",
             "ROL",
             "RON",
             "RSD",
             "RUB",
             "RWF",
             "SAR",
             "SBD",
             "SCR",
             "SDD",
             "SDG",
             "SDP",
             "SEK",
             "SGD",
             "SHP",
             "SIT",
             "SKK",
             "SLL",
             "SOS",
             "SRD",
             "SRG",
             "STD",
             "STN",
             "SVC",
             "SYP",
             "SZL",
             "THB",
             "TJS",
             "TMM",
             "TMT",
             "TND",
             "TOP",
             "TRL",
             "TRY",
             "TTD",
             "TWD",
             "TZS",
             "UAH",
             "UGS",
             "UGX",
             "USD",
             "UYP",
             "UYU",
             "UZS",
             "VEB",
             "VEF",
             "VES",
             "VND",
             "VUV",
             "WST",
             "XAF",
             "XAG",
             "XAU",
             "XBT",
             "XCD",
             "XEU",
             "XOF",
             "XPD",
             "XPF",
             "XPT",
             "YER",
             "YUN",
             "ZAR",
             "ZMK",
             "ZMW",
             "ZWD",
             "ZWL"
          ]
       },
       "endpoint":"spot",
       "request_time":"2019-03-18T21:54:31+00:00",
       "skipped_currency_pairs":[
 
       ]
    },
    "quotes":[
       {
          "base_currency":"EUR",
          "quote_currency":"ADF",
          "bid":"6.55957",
          "ask":"6.55957",
          "midpoint":"6.55957"
       },
       {
          "base_currency":"EUR",
          "quote_currency":"ADP",
          "bid":"166.386",
          "ask":"166.386",
          "midpoint":"166.386"
       },
       {
          "base_currency":"EUR",
          "quote_currency":"AED",
          "bid":"4.16261",
          "ask":"4.16465",
          "midpoint":"4.16363"
       },
       {
          "base_currency":"EUR",
          "quote_currency":"AFA",
          "bid":"85.4466",
          "ask":"85.7429",
          "midpoint":"85.5948"
       },
       {
          "base_currency":"EUR",
          "quote_currency":"AFN",
          "bid":"85.4466",
          "ask":"85.7429",
          "midpoint":"85.5948"
       },
       {
          "base_currency":"EUR",
          "quote_currency":"ALL",
          "bid":"124.738",
          "ask":"125.437",
          "midpoint":"125.088"
       },
       {
          "base_currency":"EUR",
          "quote_currency":"AMD",
          "bid":"551.172",
          "ask":"551.822",
          "midpoint":"551.497"
       },
       {
          "base_currency":"EUR",
          "quote_currency":"ANG",
          "bid":"2.02891",
          "ask":"2.02922",
          "midpoint":"2.02906"
       },
       {
          "base_currency":"EUR",
          "quote_currency":"AOA",
          "bid":"355.932",
          "ask":"359.582",
          "midpoint":"357.757"
       },
       {
          "base_currency":"EUR",
          "quote_currency":"AON",
          "bid":"355.932",
          "ask":"359.582",
          "midpoint":"357.757"
       },
       {
          "base_currency":"EUR",
          "quote_currency":"ARS",
          "bid":"45.3705",
          "ask":"45.3887",
          "midpoint":"45.3796"
       },
       {
          "base_currency":"EUR",
          "quote_currency":"ATS",
          "bid":"13.7603",
          "ask":"13.7603",
          "midpoint":"13.7603"
       },
       {
          "base_currency":"EUR",
          "quote_currency":"AUD",
          "bid":"1.59620",
          "ask":"1.59661",
          "midpoint":"1.59640"
       },
       {
          "base_currency":"EUR",
          "quote_currency":"AWG",
          "bid":"2.02324",
          "ask":"2.04565",
          "midpoint":"2.03444"
       },
       {
          "base_currency":"EUR",
          "quote_currency":"AZM",
          "bid":"9618.91",
          "ask":"9665.70",
          "midpoint":"9642.30"
       },
       {
          "base_currency":"EUR",
          "quote_currency":"AZN",
          "bid":"1.92378",
          "ask":"1.93314",
          "midpoint":"1.92846"
       },
       {
          "base_currency":"EUR",
          "quote_currency":"BAM",
          "bid":"1.95583",
          "ask":"1.95583",
          "midpoint":"1.95583"
       },
       {
          "base_currency":"EUR",
          "quote_currency":"BBD",
          "bid":"2.26694",
          "ask":"2.26728",
          "midpoint":"2.26711"
       },
       {
          "base_currency":"EUR",
          "quote_currency":"BDT",
          "bid":"94.4402",
          "ask":"96.4042",
          "midpoint":"95.4222"
       },
       {
          "base_currency":"EUR",
          "quote_currency":"BEF",
          "bid":"40.3399",
          "ask":"40.3399",
          "midpoint":"40.3399"
       },
       {
          "base_currency":"EUR",
          "quote_currency":"BGL",
          "bid":"1.95583",
          "ask":"1.95583",
          "midpoint":"1.95583"
       },
       {
          "base_currency":"EUR",
          "quote_currency":"BGN",
          "bid":"1.95583",
          "ask":"1.95583",
          "midpoint":"1.95583"
       },
       {
          "base_currency":"EUR",
          "quote_currency":"BHD",
          "bid":"0.424297",
          "ask":"0.430052",
          "midpoint":"0.427174"
       },
       {
          "base_currency":"EUR",
          "quote_currency":"BIF",
          "bid":"2045.06",
          "ask":"2094.68",
          "midpoint":"2069.87"
       },
       {
          "base_currency":"EUR",
          "quote_currency":"BMD",
          "bid":"1.13347",
          "ask":"1.13364",
          "midpoint":"1.13356"
       },
       {
          "base_currency":"EUR",
          "quote_currency":"BND",
          "bid":"1.53145",
          "ask":"1.53224",
          "midpoint":"1.53184"
       },
       {
          "base_currency":"EUR",
          "quote_currency":"BOB",
          "bid":"7.70051",
          "ask":"7.98774",
          "midpoint":"7.84412"
       },
       {
          "base_currency":"EUR",
          "quote_currency":"BRL",
          "bid":"4.29608",
          "ask":"4.30109",
          "midpoint":"4.29858"
       },
       {
          "base_currency":"EUR",
          "quote_currency":"BSD",
          "bid":"1.13347",
          "ask":"1.13364",
          "midpoint":"1.13356"
       },
       {
          "base_currency":"EUR",
          "quote_currency":"BTC",
          "bid":"0.000285059",
          "ask":"0.000285102",
          "midpoint":"0.000285080"
       },
       {
          "base_currency":"EUR",
          "quote_currency":"BTN",
          "bid":"77.5441",
          "ask":"77.8391",
          "midpoint":"77.6916"
       },
       {
          "base_currency":"EUR",
          "quote_currency":"BWP",
          "bid":"11.8968",
          "ask":"12.3838",
          "midpoint":"12.1403"
       },
       {
          "base_currency":"EUR",
          "quote_currency":"BYN",
          "bid":"2.38675",
          "ask":"2.39209",
          "midpoint":"2.38942"
       },
       {
          "base_currency":"EUR",
          "quote_currency":"BYR",
          "bid":"23867.5",
          "ask":"23920.9",
          "midpoint":"23894.2"
       },
       {
          "base_currency":"EUR",
          "quote_currency":"BZD",
          "bid":"2.24971",
          "ask":"2.31977",
          "midpoint":"2.28474"
       },
       {
          "base_currency":"EUR",
          "quote_currency":"CAD",
          "bid":"1.51137",
          "ask":"1.51211",
          "midpoint":"1.51174"
       },
       {
          "base_currency":"EUR",
          "quote_currency":"CDF",
          "bid":"1830.44",
          "ask":"1876.06",
          "midpoint":"1853.25"
       },
       {
          "base_currency":"EUR",
          "quote_currency":"CFP",
          "bid":"119.332",
          "ask":"119.332",
          "midpoint":"119.332"
       },
       {
          "base_currency":"EUR",
          "quote_currency":"CHF",
          "bid":"1.13448",
          "ask":"1.13538",
          "midpoint":"1.13493"
       },
       {
          "base_currency":"EUR",
          "quote_currency":"CLP",
          "bid":"754.517",
          "ask":"755.259",
          "midpoint":"754.888"
       },
       {
          "base_currency":"EUR",
          "quote_currency":"CNH",
          "bid":"7.61705",
          "ask":"7.61982",
          "midpoint":"7.61844"
       },
       {
          "base_currency":"EUR",
          "quote_currency":"CNY",
          "bid":"7.60785",
          "ask":"7.61069",
          "midpoint":"7.60927"
       },
       {
          "base_currency":"EUR",
          "quote_currency":"COP",
          "bid":"3511.13",
          "ask":"3515.34",
          "midpoint":"3513.24"
       },
       {
          "base_currency":"EUR",
          "quote_currency":"CRC",
          "bid":"668.560",
          "ask":"688.307",
          "midpoint":"678.434"
       },
       {
          "base_currency":"EUR",
          "quote_currency":"CSD",
          "bid":"117.703",
          "ask":"118.190",
          "midpoint":"117.946"
       },
       {
          "base_currency":"EUR",
          "quote_currency":"CSK",
          "bid":"25.5965",
          "ask":"25.6176",
          "midpoint":"25.6070"
       },
       {
          "base_currency":"EUR",
          "quote_currency":"CUC",
          "bid":"1.13347",
          "ask":"1.13364",
          "midpoint":"1.13356"
       },
       {
          "base_currency":"EUR",
          "quote_currency":"CUP",
          "bid":"28.3368",
          "ask":"28.3410",
          "midpoint":"28.3389"
       },
       {
          "base_currency":"EUR",
          "quote_currency":"CVE",
          "bid":"110.265",
          "ask":"110.265",
          "midpoint":"110.265"
       },
       {
          "base_currency":"EUR",
          "quote_currency":"CYP",
          "bid":"0.585274",
          "ask":"0.585274",
          "midpoint":"0.585274"
       },
       {
          "base_currency":"EUR",
          "quote_currency":"CZK",
          "bid":"25.5965",
          "ask":"25.6176",
          "midpoint":"25.6070"
       },
       {
          "base_currency":"EUR",
          "quote_currency":"DEM",
          "bid":"1.95583",
          "ask":"1.95583",
          "midpoint":"1.95583"
       },
       {
          "base_currency":"EUR",
          "quote_currency":"DJF",
          "bid":"201.429",
          "ask":"201.459",
          "midpoint":"201.444"
       },
       {
          "base_currency":"EUR",
          "quote_currency":"DKK",
          "bid":"7.46170",
          "ask":"7.46317",
          "midpoint":"7.46244"
       },
       {
          "base_currency":"EUR",
          "quote_currency":"DOP",
          "bid":"57.0192",
          "ask":"57.6059",
          "midpoint":"57.3126"
       },
       {
          "base_currency":"EUR",
          "quote_currency":"DZD",
          "bid":"134.173",
          "ask":"135.893",
          "midpoint":"135.033"
       },
       {
          "base_currency":"EUR",
          "quote_currency":"ECS",
          "bid":"27309.8",
          "ask":"29006.4",
          "midpoint":"28158.1"
       },
       {
          "base_currency":"EUR",
          "quote_currency":"EEK",
          "bid":"15.6466",
          "ask":"15.6466",
          "midpoint":"15.6466"
       },
       {
          "base_currency":"EUR",
          "quote_currency":"EGP",
          "bid":"19.5777",
          "ask":"19.6659",
          "midpoint":"19.6218"
       },
       {
          "base_currency":"EUR",
          "quote_currency":"ERN",
          "bid":"17.0020",
          "ask":"17.0046",
          "midpoint":"17.0033"
       },
       {
          "base_currency":"EUR",
          "quote_currency":"ESP",
          "bid":"166.386",
          "ask":"166.386",
          "midpoint":"166.386"
       },
       {
          "base_currency":"EUR",
          "quote_currency":"ETB",
          "bid":"32.0205",
          "ask":"32.8302",
          "midpoint":"32.4254"
       },
       {
          "base_currency":"EUR",
          "quote_currency":"ETH",
          "bid":"0.00823743",
          "ask":"0.00823926",
          "midpoint":"0.00823834"
       },
       {
          "base_currency":"EUR",
          "quote_currency":"FIM",
          "bid":"5.94573",
          "ask":"5.94573",
          "midpoint":"5.94573"
       },
       {
          "base_currency":"EUR",
          "quote_currency":"FJD",
          "bid":"2.38008",
          "ask":"2.40797",
          "midpoint":"2.39402"
       },
       {
          "base_currency":"EUR",
          "quote_currency":"FKP",
          "bid":"0.855470",
          "ask":"0.855830",
          "midpoint":"0.855650"
       },
       {
          "base_currency":"EUR",
          "quote_currency":"FRF",
          "bid":"6.55957",
          "ask":"6.55957",
          "midpoint":"6.55957"
       },
       {
          "base_currency":"EUR",
          "quote_currency":"GBP",
          "bid":"0.855470",
          "ask":"0.855830",
          "midpoint":"0.855650"
       },
       {
          "base_currency":"EUR",
          "quote_currency":"GEL",
          "bid":"3.02863",
          "ask":"3.05176",
          "midpoint":"3.04020"
       },
       {
          "base_currency":"EUR",
          "quote_currency":"GHC",
          "bid":"60878.7",
          "ask":"61046.5",
          "midpoint":"60962.6"
       },
       {
          "base_currency":"EUR",
          "quote_currency":"GHS",
          "bid":"6.08787",
          "ask":"6.10465",
          "midpoint":"6.09626"
       },
       {
          "base_currency":"EUR",
          "quote_currency":"GIP",
          "bid":"0.855470",
          "ask":"0.855830",
          "midpoint":"0.855650"
       },
       {
          "base_currency":"EUR",
          "quote_currency":"GMD",
          "bid":"55.9141",
          "ask":"56.4893",
          "midpoint":"56.2017"
       },
       {
          "base_currency":"EUR",
          "quote_currency":"GNF",
          "bid":"10318.0",
          "ask":"10517.9",
          "midpoint":"10418.0"
       },
       {
          "base_currency":"EUR",
          "quote_currency":"GRD",
          "bid":"340.750",
          "ask":"340.750",
          "midpoint":"340.750"
       },
       {
          "base_currency":"EUR",
          "quote_currency":"GTQ",
          "bid":"8.61891",
          "ask":"8.82159",
          "midpoint":"8.72025"
       },
       {
          "base_currency":"EUR",
          "quote_currency":"GYD",
          "bid":"230.502",
          "ask":"243.353",
          "midpoint":"236.928"
       },
       {
          "base_currency":"EUR",
          "quote_currency":"HKD",
          "bid":"8.89725",
          "ask":"8.90005",
          "midpoint":"8.89865"
       },
       {
          "base_currency":"EUR",
          "quote_currency":"HNL",
          "bid":"27.5898",
          "ask":"27.8717",
          "midpoint":"27.7308"
       },
       {
          "base_currency":"EUR",
          "quote_currency":"HRK",
          "bid":"7.40995",
          "ask":"7.42211",
          "midpoint":"7.41603"
       },
       {
          "base_currency":"EUR",
          "quote_currency":"HTG",
          "bid":"93.0511",
          "ask":"94.6300",
          "midpoint":"93.8406"
       },
       {
          "base_currency":"EUR",
          "quote_currency":"HUF",
          "bid":"313.750",
          "ask":"314.220",
          "midpoint":"313.985"
       },
       {
          "base_currency":"EUR",
          "quote_currency":"IDR",
          "bid":"16109.7",
          "ask":"16117.1",
          "midpoint":"16113.4"
       },
       {
          "base_currency":"EUR",
          "quote_currency":"IEP",
          "bid":"0.787564",
          "ask":"0.787564",
          "midpoint":"0.787564"
       },
       {
          "base_currency":"EUR",
          "quote_currency":"ILS",
          "bid":"4.08244",
          "ask":"4.09042",
          "midpoint":"4.08643"
       },
       {
          "base_currency":"EUR",
          "quote_currency":"INR",
          "bid":"77.5441",
          "ask":"77.8391",
          "midpoint":"77.6916"
       },
       {
          "base_currency":"EUR",
          "quote_currency":"IQD",
          "bid":"1345.43",
          "ask":"1352.43",
          "midpoint":"1348.93"
       },
       {
          "base_currency":"EUR",
          "quote_currency":"IRR",
          "bid":"47605.7",
          "ask":"47731.9",
          "midpoint":"47668.8"
       },
       {
          "base_currency":"EUR",
          "quote_currency":"ISK",
          "bid":"132.486",
          "ask":"133.016",
          "midpoint":"132.751"
       },
       {
          "base_currency":"EUR",
          "quote_currency":"ITL",
          "bid":"1936.27",
          "ask":"1936.27",
          "midpoint":"1936.27"
       },
       {
          "base_currency":"EUR",
          "quote_currency":"JMD",
          "bid":"139.938",
          "ask":"142.045",
          "midpoint":"140.992"
       },
       {
          "base_currency":"EUR",
          "quote_currency":"JOD",
          "bid":"0.803630",
          "ask":"0.803751",
          "midpoint":"0.803690"
       },
       {
          "base_currency":"EUR",
          "quote_currency":"JPY",
          "bid":"126.300",
          "ask":"126.350",
          "midpoint":"126.325"
       },
       {
          "base_currency":"EUR",
          "quote_currency":"KES",
          "bid":"113.290",
          "ask":"114.872",
          "midpoint":"114.081"
       },
       {
          "base_currency":"EUR",
          "quote_currency":"KGS",
          "bid":"79.1075",
          "ask":"79.1477",
          "midpoint":"79.1276"
       },
       {
          "base_currency":"EUR",
          "quote_currency":"KHR",
          "bid":"4501.63",
          "ask":"4530.65",
          "midpoint":"4516.14"
       },
       {
          "base_currency":"EUR",
          "quote_currency":"KMF",
          "bid":"491.968",
          "ask":"491.968",
          "midpoint":"491.968"
       },
       {
          "base_currency":"EUR",
          "quote_currency":"KPW",
          "bid":"153.018",
          "ask":"153.041",
          "midpoint":"153.030"
       },
       {
          "base_currency":"EUR",
          "quote_currency":"KRW",
          "bid":"1282.29",
          "ask":"1284.75",
          "midpoint":"1283.52"
       },
       {
          "base_currency":"EUR",
          "quote_currency":"KWD",
          "bid":"0.343719",
          "ask":"0.345471",
          "midpoint":"0.344595"
       },
       {
          "base_currency":"EUR",
          "quote_currency":"KYD",
          "bid":"0.944558",
          "ask":"0.944700",
          "midpoint":"0.944629"
       },
       {
          "base_currency":"EUR",
          "quote_currency":"KZT",
          "bid":"425.442",
          "ask":"426.101",
          "midpoint":"425.772"
       },
       {
          "base_currency":"EUR",
          "quote_currency":"LAK",
          "bid":"9718.37",
          "ask":"9753.27",
          "midpoint":"9735.82"
       },
       {
          "base_currency":"EUR",
          "quote_currency":"LBP",
          "bid":"1708.71",
          "ask":"1708.96",
          "midpoint":"1708.84"
       },
       {
          "base_currency":"EUR",
          "quote_currency":"LKR",
          "bid":"202.001",
          "ask":"202.275",
          "midpoint":"202.138"
       },
       {
          "base_currency":"EUR",
          "quote_currency":"LRD",
          "bid":"183.061",
          "ask":"184.506",
          "midpoint":"183.784"
       },
       {
          "base_currency":"EUR",
          "quote_currency":"LSL",
          "bid":"16.3538",
          "ask":"16.3866",
          "midpoint":"16.3702"
       },
       {
          "base_currency":"EUR",
          "quote_currency":"LTC",
          "bid":"0.0191529",
          "ask":"0.0191688",
          "midpoint":"0.0191608"
       },
       {
          "base_currency":"EUR",
          "quote_currency":"LTL",
          "bid":"3.45280",
          "ask":"3.45280",
          "midpoint":"3.45280"
       },
       {
          "base_currency":"EUR",
          "quote_currency":"LUF",
          "bid":"40.3399",
          "ask":"40.3399",
          "midpoint":"40.3399"
       },
       {
          "base_currency":"EUR",
          "quote_currency":"LVL",
          "bid":"0.702804",
          "ask":"0.702804",
          "midpoint":"0.702804"
       },
       {
          "base_currency":"EUR",
          "quote_currency":"LYD",
          "bid":"1.56039",
          "ask":"1.58727",
          "midpoint":"1.57383"
       },
       {
          "base_currency":"EUR",
          "quote_currency":"MAD",
          "bid":"10.8569",
          "ask":"10.8926",
          "midpoint":"10.8748"
       },
       {
          "base_currency":"EUR",
          "quote_currency":"MDL",
          "bid":"19.3149",
          "ask":"19.6738",
          "midpoint":"19.4944"
       },
       {
          "base_currency":"EUR",
          "quote_currency":"MGA",
          "bid":"3938.81",
          "ask":"3996.08",
          "midpoint":"3967.44"
       },
       {
          "base_currency":"EUR",
          "quote_currency":"MGF",
          "bid":"10371.3",
          "ask":"10373.3",
          "midpoint":"10372.3"
       },
       {
          "base_currency":"EUR",
          "quote_currency":"MKD",
          "bid":"61.0561",
          "ask":"62.0084",
          "midpoint":"61.5322"
       },
       {
          "base_currency":"EUR",
          "quote_currency":"MMK",
          "bid":"1729.85",
          "ask":"1754.31",
          "midpoint":"1742.08"
       },
       {
          "base_currency":"EUR",
          "quote_currency":"MNT",
          "bid":"2960.62",
          "ask":"2969.00",
          "midpoint":"2964.81"
       },
       {
          "base_currency":"EUR",
          "quote_currency":"MOP",
          "bid":"9.16417",
          "ask":"9.16705",
          "midpoint":"9.16561"
       },
       {
          "base_currency":"EUR",
          "quote_currency":"MRO",
          "bid":"411.393",
          "ask":"417.690",
          "midpoint":"414.542"
       },
       {
          "base_currency":"EUR",
          "quote_currency":"MRU",
          "bid":"41.1393",
          "ask":"41.7690",
          "midpoint":"41.4542"
       },
       {
          "base_currency":"EUR",
          "quote_currency":"MTL",
          "bid":"0.429300",
          "ask":"0.429300",
          "midpoint":"0.429300"
       },
       {
          "base_currency":"EUR",
          "quote_currency":"MUR",
          "bid":"37.9384",
          "ask":"40.5435",
          "midpoint":"39.2410"
       },
       {
          "base_currency":"EUR",
          "quote_currency":"MVR",
          "bid":"17.3818",
          "ask":"17.8945",
          "midpoint":"17.6382"
       },
       {
          "base_currency":"EUR",
          "quote_currency":"MWK",
          "bid":"809.660",
          "ask":"839.596",
          "midpoint":"824.628"
       },
       {
          "base_currency":"EUR",
          "quote_currency":"MXN",
          "bid":"21.5987",
          "ask":"21.6239",
          "midpoint":"21.6113"
       },
       {
          "base_currency":"EUR",
          "quote_currency":"MXP",
          "bid":"21.5987",
          "ask":"21.6239",
          "midpoint":"21.6113"
       },
       {
          "base_currency":"EUR",
          "quote_currency":"MYR",
          "bid":"4.62002",
          "ask":"4.62582",
          "midpoint":"4.62292"
       },
       {
          "base_currency":"EUR",
          "quote_currency":"MZM",
          "bid":"70388.5",
          "ask":"71702.7",
          "midpoint":"71045.6"
       },
       {
          "base_currency":"EUR",
          "quote_currency":"MZN",
          "bid":"70.3885",
          "ask":"71.7027",
          "midpoint":"71.0456"
       },
       {
          "base_currency":"EUR",
          "quote_currency":"NAD",
          "bid":"16.3538",
          "ask":"16.3866",
          "midpoint":"16.3702"
       },
       {
          "base_currency":"EUR",
          "quote_currency":"NGN",
          "bid":"406.066",
          "ask":"410.094",
          "midpoint":"408.080"
       },
       {
          "base_currency":"EUR",
          "quote_currency":"NIO",
          "bid":"36.9058",
          "ask":"37.4781",
          "midpoint":"37.1920"
       },
       {
          "base_currency":"EUR",
          "quote_currency":"NLG",
          "bid":"2.20371",
          "ask":"2.20371",
          "midpoint":"2.20371"
       },
       {
          "base_currency":"EUR",
          "quote_currency":"NOK",
          "bid":"9.68575",
          "ask":"9.69212",
          "midpoint":"9.68894"
       },
       {
          "base_currency":"EUR",
          "quote_currency":"NPR",
          "bid":"123.707",
          "ask":"125.760",
          "midpoint":"124.734"
       },
       {
          "base_currency":"EUR",
          "quote_currency":"NZD",
          "bid":"1.65463",
          "ask":"1.65536",
          "midpoint":"1.65500"
       },
       {
          "base_currency":"EUR",
          "quote_currency":"OMR",
          "bid":"0.435264",
          "ask":"0.437636",
          "midpoint":"0.436450"
       },
       {
          "base_currency":"EUR",
          "quote_currency":"PAB",
          "bid":"1.13347",
          "ask":"1.13364",
          "midpoint":"1.13356"
       },
       {
          "base_currency":"EUR",
          "quote_currency":"PEN",
          "bid":"3.74385",
          "ask":"3.76652",
          "midpoint":"3.75518"
       },
       {
          "base_currency":"EUR",
          "quote_currency":"PGK",
          "bid":"3.75296",
          "ask":"3.89788",
          "midpoint":"3.82542"
       },
       {
          "base_currency":"EUR",
          "quote_currency":"PHP",
          "bid":"59.8302",
          "ask":"59.9469",
          "midpoint":"59.8886"
       },
       {
          "base_currency":"EUR",
          "quote_currency":"PKR",
          "bid":"158.249",
          "ask":"158.443",
          "midpoint":"158.346"
       },
       {
          "base_currency":"EUR",
          "quote_currency":"PLN",
          "bid":"4.28857",
          "ask":"4.29335",
          "midpoint":"4.29096"
       },
       {
          "base_currency":"EUR",
          "quote_currency":"PLZ",
          "bid":"4.28857",
          "ask":"4.29335",
          "midpoint":"4.29096"
       },
       {
          "base_currency":"EUR",
          "quote_currency":"PTE",
          "bid":"200.482",
          "ask":"200.482",
          "midpoint":"200.482"
       },
       {
          "base_currency":"EUR",
          "quote_currency":"PYG",
          "bid":"6878.97",
          "ask":"7038.09",
          "midpoint":"6958.53"
       },
       {
          "base_currency":"EUR",
          "quote_currency":"QAR",
          "bid":"4.12628",
          "ask":"4.12832",
          "midpoint":"4.12730"
       },
       {
          "base_currency":"EUR",
          "quote_currency":"ROL",
          "bid":"47371.1",
          "ask":"47721.1",
          "midpoint":"47546.1"
       },
       {
          "base_currency":"EUR",
          "quote_currency":"RON",
          "bid":"4.73711",
          "ask":"4.77211",
          "midpoint":"4.75461"
       },
       {
          "base_currency":"EUR",
          "quote_currency":"RSD",
          "bid":"117.703",
          "ask":"118.190",
          "midpoint":"117.946"
       },
       {
          "base_currency":"EUR",
          "quote_currency":"RUB",
          "bid":"72.8862",
          "ask":"72.9623",
          "midpoint":"72.9242"
       },
       {
          "base_currency":"EUR",
          "quote_currency":"RWF",
          "bid":"1001.83",
          "ask":"1022.95",
          "midpoint":"1012.39"
       },
       {
          "base_currency":"EUR",
          "quote_currency":"SAR",
          "bid":"4.24521",
          "ask":"4.25718",
          "midpoint":"4.25120"
       },
       {
          "base_currency":"EUR",
          "quote_currency":"SBD",
          "bid":"8.96024",
          "ask":"9.52639",
          "midpoint":"9.24332"
       },
       {
          "base_currency":"EUR",
          "quote_currency":"SCR",
          "bid":"14.9374",
          "ask":"16.3930",
          "midpoint":"15.6652"
       },
       {
          "base_currency":"EUR",
          "quote_currency":"SDD",
          "bid":"5378.61",
          "ask":"5421.49",
          "midpoint":"5400.05"
       },
       {
          "base_currency":"EUR",
          "quote_currency":"SDG",
          "bid":"53.7861",
          "ask":"54.2149",
          "midpoint":"54.0005"
       },
       {
          "base_currency":"EUR",
          "quote_currency":"SDP",
          "bid":"2562.78",
          "ask":"2575.97",
          "midpoint":"2569.38"
       },
       {
          "base_currency":"EUR",
          "quote_currency":"SEK",
          "bid":"10.4619",
          "ask":"10.4651",
          "midpoint":"10.4635"
       },
       {
          "base_currency":"EUR",
          "quote_currency":"SGD",
          "bid":"1.53145",
          "ask":"1.53224",
          "midpoint":"1.53184"
       },
       {
          "base_currency":"EUR",
          "quote_currency":"SHP",
          "bid":"0.855470",
          "ask":"0.855830",
          "midpoint":"0.855650"
       },
       {
          "base_currency":"EUR",
          "quote_currency":"SIT",
          "bid":"239.640",
          "ask":"239.640",
          "midpoint":"239.640"
       },
       {
          "base_currency":"EUR",
          "quote_currency":"SKK",
          "bid":"30.1260",
          "ask":"30.1260",
          "midpoint":"30.1260"
       },
       {
          "base_currency":"EUR",
          "quote_currency":"SLL",
          "bid":"9815.85",
          "ask":"9987.37",
          "midpoint":"9901.61"
       },
       {
          "base_currency":"EUR",
          "quote_currency":"SOS",
          "bid":"644.944",
          "ask":"679.050",
          "midpoint":"661.997"
       },
       {
          "base_currency":"EUR",
          "quote_currency":"SRD",
          "bid":"8.39675",
          "ask":"8.49663",
          "midpoint":"8.44669"
       },
       {
          "base_currency":"EUR",
          "quote_currency":"SRG",
          "bid":"8396.75",
          "ask":"8496.63",
          "midpoint":"8446.69"
       },
       {
          "base_currency":"EUR",
          "quote_currency":"STD",
          "bid":"24460.3",
          "ask":"24532.0",
          "midpoint":"24496.2"
       },
       {
          "base_currency":"EUR",
          "quote_currency":"STN",
          "bid":"24.4603",
          "ask":"24.5320",
          "midpoint":"24.4962"
       },
       {
          "base_currency":"EUR",
          "quote_currency":"SVC",
          "bid":"9.91786",
          "ask":"9.91935",
          "midpoint":"9.91860"
       },
       {
          "base_currency":"EUR",
          "quote_currency":"SYP",
          "bid":"243.186",
          "ask":"243.563",
          "midpoint":"243.374"
       },
       {
          "base_currency":"EUR",
          "quote_currency":"SZL",
          "bid":"16.3538",
          "ask":"16.3866",
          "midpoint":"16.3702"
       },
       {
          "base_currency":"EUR",
          "quote_currency":"THB",
          "bid":"35.7814",
          "ask":"36.0588",
          "midpoint":"35.9201"
       },
       {
          "base_currency":"EUR",
          "quote_currency":"TJS",
          "bid":"10.6339",
          "ask":"10.7608",
          "midpoint":"10.6974"
       },
       {
          "base_currency":"EUR",
          "quote_currency":"TMM",
          "bid":"19269.0",
          "ask":"20405.5",
          "midpoint":"19837.2"
       },
       {
          "base_currency":"EUR",
          "quote_currency":"TMT",
          "bid":"3.85380",
          "ask":"4.08110",
          "midpoint":"3.96745"
       },
       {
          "base_currency":"EUR",
          "quote_currency":"TND",
          "bid":"3.40568",
          "ask":"3.41866",
          "midpoint":"3.41217"
       },
       {
          "base_currency":"EUR",
          "quote_currency":"TOP",
          "bid":"2.56742",
          "ask":"2.63322",
          "midpoint":"2.60032"
       },
       {
          "base_currency":"EUR",
          "quote_currency":"TRL",
          "bid":"6196740",
          "ask":"6201550",
          "midpoint":"6199140"
       },
       {
          "base_currency":"EUR",
          "quote_currency":"TRY",
          "bid":"6.19674",
          "ask":"6.20155",
          "midpoint":"6.19914"
       },
       {
          "base_currency":"EUR",
          "quote_currency":"TTD",
          "bid":"7.58325",
          "ask":"7.76334",
          "midpoint":"7.67330"
       },
       {
          "base_currency":"EUR",
          "quote_currency":"TWD",
          "bid":"34.8769",
          "ask":"34.8997",
          "midpoint":"34.8883"
       },
       {
          "base_currency":"EUR",
          "quote_currency":"TZS",
          "bid":"2651.36",
          "ask":"2661.39",
          "midpoint":"2656.38"
       },
       {
          "base_currency":"EUR",
          "quote_currency":"UAH",
          "bid":"30.6092",
          "ask":"30.8973",
          "midpoint":"30.7532"
       },
       {
          "base_currency":"EUR",
          "quote_currency":"UGS",
          "bid":"4173.55",
          "ask":"4224.79",
          "midpoint":"4199.17"
       },
       {
          "base_currency":"EUR",
          "quote_currency":"UGX",
          "bid":"4173.55",
          "ask":"4224.79",
          "midpoint":"4199.17"
       },
       {
          "base_currency":"EUR",
          "quote_currency":"USD",
          "bid":"1.13347",
          "ask":"1.13364",
          "midpoint":"1.13356"
       },
       {
          "base_currency":"EUR",
          "quote_currency":"UYP",
          "bid":"37.9044",
          "ask":"38.0801",
          "midpoint":"37.9922"
       },
       {
          "base_currency":"EUR",
          "quote_currency":"UYU",
          "bid":"37.9044",
          "ask":"38.0801",
          "midpoint":"37.9922"
       },
       {
          "base_currency":"EUR",
          "quote_currency":"UZS",
          "bid":"9461.07",
          "ask":"9553.18",
          "midpoint":"9507.12"
       },
       {
          "base_currency":"EUR",
          "quote_currency":"VEB",
          "bid":"372669000000",
          "ask":"373076000000",
          "midpoint":"372872000000"
       },
       {
          "base_currency":"EUR",
          "quote_currency":"VEF",
          "bid":"372669000",
          "ask":"373076000",
          "midpoint":"372872000"
       },
       {
          "base_currency":"EUR",
          "quote_currency":"VES",
          "bid":"3726.69",
          "ask":"3730.76",
          "midpoint":"3728.72"
       },
       {
          "base_currency":"EUR",
          "quote_currency":"VND",
          "bid":"26295.4",
          "ask":"26306.7",
          "midpoint":"26301.0"
       },
       {
          "base_currency":"EUR",
          "quote_currency":"VUV",
          "bid":"126.813",
          "ask":"129.099",
          "midpoint":"127.956"
       },
       {
          "base_currency":"EUR",
          "quote_currency":"WST",
          "bid":"2.99157",
          "ask":"2.99655",
          "midpoint":"2.99406"
       },
       {
          "base_currency":"EUR",
          "quote_currency":"XAF",
          "bid":"655.957",
          "ask":"655.957",
          "midpoint":"655.957"
       },
       {
          "base_currency":"EUR",
          "quote_currency":"XAG",
          "bid":"0.0738064",
          "ask":"0.0738896",
          "midpoint":"0.0738480"
       },
       {
          "base_currency":"EUR",
          "quote_currency":"XAU",
          "bid":"0.000869224",
          "ask":"0.000869711",
          "midpoint":"0.000869468"
       },
       {
          "base_currency":"EUR",
          "quote_currency":"XBT",
          "bid":"0.000285059",
          "ask":"0.000285102",
          "midpoint":"0.000285080"
       },
       {
          "base_currency":"EUR",
          "quote_currency":"XCD",
          "bid":"3.06037",
          "ask":"3.06083",
          "midpoint":"3.06060"
       },
       {
          "base_currency":"EUR",
          "quote_currency":"XEU",
          "bid":"1.00000",
          "ask":"1.00000",
          "midpoint":"1.00000"
       },
       {
          "base_currency":"EUR",
          "quote_currency":"XOF",
          "bid":"655.957",
          "ask":"655.957",
          "midpoint":"655.957"
       },
       {
          "base_currency":"EUR",
          "quote_currency":"XPD",
          "bid":"0.000713547",
          "ask":"0.000715908",
          "midpoint":"0.000714728"
       },
       {
          "base_currency":"EUR",
          "quote_currency":"XPF",
          "bid":"119.332",
          "ask":"119.332",
          "midpoint":"119.332"
       },
       {
          "base_currency":"EUR",
          "quote_currency":"XPT",
          "bid":"0.00135244",
          "ask":"0.00135894",
          "midpoint":"0.00135569"
       },
       {
          "base_currency":"EUR",
          "quote_currency":"YER",
          "bid":"282.886",
          "ask":"283.552",
          "midpoint":"283.219"
       },
       {
          "base_currency":"EUR",
          "quote_currency":"YUN",
          "bid":"117.703",
          "ask":"118.190",
          "midpoint":"117.946"
       },
       {
          "base_currency":"EUR",
          "quote_currency":"ZAR",
          "bid":"16.3538",
          "ask":"16.3866",
          "midpoint":"16.3702"
       },
       {
          "base_currency":"EUR",
          "quote_currency":"ZMK",
          "bid":"5867.07",
          "ask":"6041.05",
          "midpoint":"5954.06"
       },
       {
          "base_currency":"EUR",
          "quote_currency":"ZMW",
          "bid":"13.6134",
          "ask":"13.6644",
          "midpoint":"13.6389"
       },
       {
          "base_currency":"EUR",
          "quote_currency":"ZWD",
          "bid":"423.124",
          "ask":"426.589",
          "midpoint":"424.856"
       },
       {
          "base_currency":"EUR",
          "quote_currency":"ZWL",
          "bid":"410.203",
          "ask":"410.264",
          "midpoint":"410.234"
       }
    ]
 }